langchain_wenxin/__about__.py
langchain_wenxin/__init__.py
langchain_wenxin/chat_models.py
langchain_wenxin/client.py
langchain_wenxin/embeddings.py
langchain_wenxin/llms.py
langchain_wenxin/retrievers.py
langchain_wenxin-0.10.2.dist-info/METADATA
langchain_wenxin-0.10.2.dist-info/WHEEL
langchain_wenxin-0.10.2.dist-info/licenses/LICENSE.txt
langchain_wenxin-0.10.2.dist-info/RECORD
