Metadata-Version: 2.1
Name: langchain-wenxin
Version: 0.10.2
Project-URL: Documentation, https://github.com/ninehills/langchain-wenxin#readme
Project-URL: Issues, https://github.com/ninehills/langchain-wenxin/issues
Project-URL: Source, https://github.com/ninehills/langchain-wenxin
Author-email: Tao Yang <swulling@gmail.com>
License-Expression: MIT
License-File: LICENSE.txt
Classifier: Development Status :: 4 - Beta
Classifier: Programming Language :: Python
Classifier: Programming Language :: Python :: 3.8
Classifier: Programming Language :: Python :: 3.9
Classifier: Programming Language :: Python :: 3.10
Classifier: Programming Language :: Python :: 3.11
Classifier: Programming Language :: Python :: Implementation :: CPython
Classifier: Programming Language :: Python :: Implementation :: PyPy
Requires-Python: >=3.8
Requires-Dist: aiohttp
Requires-Dist: langchain>=0.0.205
Requires-Dist: numpy
Requires-Dist: pydantic<2.0
Requires-Dist: requests
Requires-Dist: sseclient-py
